[
  {
    "title": "Test Title",
    "text": "Test text"
  },
  {
    "id": "8d0rghp00lyp2yozw",
    "title": "Test Title",
    "text": "Example of text. \nadded spaces below to show the scroll bar on the right                                  \n\n\n\n\n"
  },
  {
    "id": "8d0rghp00lyp2z4es",
    "title": "Example",
    "text": "text"
  },
  {
    "id": "8d0rghp00lyp2zc8o",
    "title": "Notes will",
    "text": "be"
  },
  {
    "id": "8d0rghp00lyp2znid",
    "title": "be saved here.",
    "text": "y"
  },
  {
    "id": "8d0rghp00lyp2zy8r",
    "title": "Unless you delete.",
    "text": "t"
  },
  {
    "id": "8d0rghp00lyp308st",
    "title": "via the red trashcan icon",
    "text": "t"
  }
]